odoo/addons/account_payment_mode_default_account/README.rst
odoo/addons/account_payment_mode_default_account/__init__.py
odoo/addons/account_payment_mode_default_account/__manifest__.py
odoo/addons/account_payment_mode_default_account/hooks.py
odoo/addons/account_payment_mode_default_account/i18n/account_payment_mode_default_account.pot
odoo/addons/account_payment_mode_default_account/i18n/es.po
odoo/addons/account_payment_mode_default_account/i18n/fr.po
odoo/addons/account_payment_mode_default_account/i18n/it.po
odoo/addons/account_payment_mode_default_account/models/__init__.py
odoo/addons/account_payment_mode_default_account/models/account_move.py
odoo/addons/account_payment_mode_default_account/models/account_payment_mode.py
odoo/addons/account_payment_mode_default_account/models/chart_template.py
odoo/addons/account_payment_mode_default_account/models/res_partner.py
odoo/addons/account_payment_mode_default_account/readme/CONTRIBUTORS.rst
odoo/addons/account_payment_mode_default_account/readme/DESCRIPTION.rst
odoo/addons/account_payment_mode_default_account/static/description/icon.png
odoo/addons/account_payment_mode_default_account/static/description/index.html
odoo/addons/account_payment_mode_default_account/tests/__init__.py
odoo/addons/account_payment_mode_default_account/tests/test_account_payment_mode_default_account.py
odoo/addons/account_payment_mode_default_account/views/account_payment_mode.xml
odoo14_addon_account_payment_mode_default_account-14.0.1.0.1.dev11.dist-info/METADATA
odoo14_addon_account_payment_mode_default_account-14.0.1.0.1.dev11.dist-info/WHEEL
odoo14_addon_account_payment_mode_default_account-14.0.1.0.1.dev11.dist-info/top_level.txt
odoo14_addon_account_payment_mode_default_account-14.0.1.0.1.dev11.dist-info/RECORD
