Metadata-Version: 2.1
Name: odoo14-addon-account_payment_mode_default_account
Version: 14.0.1.0.1.dev11
Summary: Set Receivable or Payable account according to payment mode
Home-page: https://github.com/OCA/bank-payment
Author: Camptocamp, Odoo Community Association (OCA)
Author-email: support@odoo-community.org
License: AGPL-3
Classifier: Programming Language :: Python
Classifier: Framework :: Odoo
Classifier: Framework :: Odoo :: 14.0
Classifier: License :: OSI Approved :: GNU Affero General Public License v3
Classifier: Development Status :: 3 - Alpha
Requires-Python: >=3.6
Requires-Dist: odoo14-addon-account-payment-partner
Requires-Dist: odoo<14.1dev,>=14.0a
